gl2f/__init__.py
gl2f/__main__.py
gl2f/__version__.py
gl2f/auth.py
gl2f/cat.py
gl2f/command_builder.py
gl2f/completion.py
gl2f/configurator.py
gl2f/dl.py
gl2f/local.py
gl2f/ls.py
gl2f/opener.py
gl2f/pages.py
gl2f/search.py
gl2f/ayame/__init__.py
gl2f/ayame/sixel.py
gl2f/ayame/terminal.py
gl2f/ayame/zen.py
gl2f/core/__init__.py
gl2f/core/article.py
gl2f/core/auth.py
gl2f/core/board.py
gl2f/core/config.py
gl2f/core/lister.py
gl2f/core/member.py
gl2f/core/pretty.py
gl2f/core/util.py
gl2f/core/local/__init__.py
gl2f/core/local/archive.py
gl2f/core/local/content.py
gl2f/core/local/fs.py
gl2f/core/local/index.py
gl2f/core/local/meta.py
gl2f/core/local/site.py
gl2f/data/completion.bash
gl2f/data/site/article.html
gl2f/data/site/common.js
gl2f/data/site/index.html
gl2f/data/site/photos.html
gl2f/data/site/style.css
gl2f-0.3.17.dist-info/licenses/LICENSE
gl2f-0.3.17.dist-info/METADATA
gl2f-0.3.17.dist-info/WHEEL
gl2f-0.3.17.dist-info/entry_points.txt
gl2f-0.3.17.dist-info/top_level.txt
gl2f-0.3.17.dist-info/RECORD
