Metadata-Version: 2.4
Name: gl2f
Version: 0.3.17
Summary: A command line tool for GL2 family
License: PolyForm-Noncommercial-1.0.0
Project-URL: Homepage, https://github.com/trnciii/gl2f-cli
Requires-Python: >=3.8
License-File: LICENSE
Requires-Dist: requests
Requires-Dist: libsixel-python
Requires-Dist: Pillow
Provides-Extra: dev
Requires-Dist: pytest; extra == "dev"
Requires-Dist: pyinstaller; extra == "dev"
Requires-Dist: pipdeptree; extra == "dev"
Requires-Dist: pip-licenses; extra == "dev"
Requires-Dist: pytest-pylint; extra == "dev"
Dynamic: license-file
